{
  "code": "DUDrLFtDHte",
  "pk": "3820086786979035998",
  "id": "3820086786979035998_62614168387",
  "caption": {
    "text": "الرجل الذي كان يحب الكلاب ليناردو بادورا .\nفي عام 2004  عادت ذاكرة إيبان ، صاحب العيادة البيطرية  البسيطة فى هافانا، الذي كان يحلم بأن يصبح كاتباً، إلى فصل من فصول حياته  وقع له عام 1977 حين تعرف الى رجل غامض رآه يتنزه عند  شاطئ البحر برفقة كلبي صيد روسيين .\nجرت عدة لقاءات بينه وبين ذلك الرجل، الذي كان مطلعاً على تفاصيل دقيقة عن رامون ميركادير، قاتل تروتسكي ، كشف له فيها النقاب عن أسرار فريدة محورها شخصية القاتل. أعاد إيبان، بفضل تلك\nالاعترافات ، بناء الخطوط التي سارت عليها حياة ليف دافيدوفيتش ، أو تروتسكي ، وخوان رامون ميركادير، الذي عُرف أيضا بجاك مورنارد، وكيف تحول الأثنان إلى ضحية وجلاد ، في واحدة من أكثر جرائم القرن العشرين دلالة ووقعا .\n لقد تشابكت حياتهما بدءا من المنفى الذي فُرض على تروتسكي عام 1929  ورحلته الشاقة إلى المنفى، ومن طفولة ميركادير في برشلونة البرجوازية ومغامراته العاطفية ومعاناته أثناء الحرب الأهلية أو بعدها ، وهو في موسكو وباريس ، قبل أن يلتقي الاثنان في المكسيك ."
  },
  "image": {
    "url": "https://scontent-ams2-1.cdninstagram.com/v/t51.82787-15/624330309_17951193969080388_3871670491631850252_n.jpg?stp=dst-jpegr_e35_tt6&_nc_cat=104&_nc_cb=04374bf5-9763b1f0&ig_cache_key=MzgyMDA4Njc4Njk3OTAzNTk5OA%3D%3D.3-ccb7-5&ccb=7-5&_nc_sid=58cdad&efg=eyJ2ZW5jb2RlX3RhZyI6InhwaWRzLjE0NDB4MTQ0MC5oZHIuQzMifQ%3D%3D&_nc_ohc=HD-lyHXVe7kQ7kNvwGFvrbI&_nc_oc=AdnA2tJFq8lNDTOzBo-fP25DwjmhYrwty0JMxntenP8oN8htJtj-mpnsSeWb8IOvKqY&_nc_ad=z-m&_nc_cid=0&_nc_zt=23&_nc_ht=scontent-ams2-1.cdninstagram.com&_nc_gid=9G9CzDjSCYoD9xYBd4NcWg&oh=00_AfuYZAcySCRq0KIp9rSDHcpegGh9YpO0lolSs_jxb-TAGQ&oe=698E35F3",
    "width": 1440,
    "height": 1440
  },
  "author": "إيبان"
}